{"title":"Falsy Bouncer","date":"2019-04-26T01:42:17.000Z","slug":"Falsy-Bouncer","tags":["freeCodeCamp"],"updated":"2019-04-26T02:31:35.875Z","content":"<h2 id=\"过滤数组中的值\">过滤数组中的值<a href=\"post/Falsy-Bouncer#过滤数组中的值\"></a></h2><hr>\n<p>过滤数组假值 （真假美猴王） 删除数组中的所有假值。 </p>\n<p>在JavaScript中，假值有false、null、0、””、undefined 和 NaN。</p>\n<p><strong>注意：</strong>如果第一个参数不是布尔值，则会将其转换为布尔值。如果省略该参数，或者其值为 0、-0、null、false、NaN、undefined、或者空字符串（””），则生成的 Boolean 对象的值为 false。</p>\n<figure class=\"highlight bash\"><table><tr><td class=\"gutter\"><pre><span class=\"line\">1</span><br><span class=\"line\">2</span><br><span class=\"line\">3</span><br><span class=\"line\">4</span><br><span class=\"line\">5</span><br><span class=\"line\">6</span><br><span class=\"line\">7</span><br></pre></td><td class=\"code\"><pre><span class=\"line\"><span class=\"keyword\">function</span> bouncer(arr) &#123;</span><br><span class=\"line\"> <span class=\"built_in\">return</span> arr.filter(<span class=\"keyword\">function</span>(val)&#123;</span><br><span class=\"line\">    <span class=\"built_in\">return</span> Boolean(val);</span><br><span class=\"line\">  &#125;);</span><br><span class=\"line\">&#125;</span><br><span class=\"line\"></span><br><span class=\"line\">bouncer([7, <span class=\"string\">\"ate\"</span>, <span class=\"string\">\"\"</span>, <span class=\"literal\">false</span>, 9]);</span><br></pre></td></tr></table></figure>\n<p>结果：</p>\n<figure class=\"highlight bash\"><table><tr><td class=\"gutter\"><pre><span class=\"line\">1</span><br></pre></td><td class=\"code\"><pre><span class=\"line\">[7, <span class=\"string\">\"ate\"</span>,  9]</span><br></pre></td></tr></table></figure>\n","next":{"title":"Hello World","slug":"hello-world"},"link":"http://yoursite.com/post/Falsy-Bouncer/","toc":[{"title":"过滤数组中的值","id":"过滤数组中的值","index":"1"}]}